n2v/__init__.py
n2v/version.py
n2v/internals/N2V_DataGenerator.py
n2v/internals/N2V_DataWrapper.py
n2v/internals/__init__.py
n2v/internals/n2v_losses.py
n2v/models/__init__.py
n2v/models/n2v_config.py
n2v/models/n2v_standard.py
n2v/nets/__init__.py
n2v/nets/blurpool.py
n2v/nets/unet.py
n2v/nets/unet_blocks.py
n2v/utils/__init__.py
n2v/utils/evaluation_utils.py
n2v/utils/export_utils.py
n2v/utils/n2v_utils.py
n2v/utils/tf.py
n2v-0.3.3.data/scripts/predictN2V.py
n2v-0.3.3.data/scripts/trainN2V.py
tests/__init__.py
tests/test_Noise2VoidDataGenerator.py
tests/test_Noise2VoidDataWrapper.py
tests/test_export_models.py
tests/test_n2v_utils.py
tests/test_read_lzw_tiff.py
tests/functional/__init__.py
tests/functional/test_prediction2D_RGB.py
tests/functional/test_prediction2D_SEM.py
tests/functional/test_prediction3D.py
tests/functional/test_training2D_RGB.py
tests/functional/test_training2D_RGB_singleNetPerChannel.py
tests/functional/test_training2D_SEM.py
tests/functional/test_training3D.py
n2v-0.3.3.dist-info/LICENSE.txt
n2v-0.3.3.dist-info/METADATA
n2v-0.3.3.dist-info/WHEEL
n2v-0.3.3.dist-info/top_level.txt
n2v-0.3.3.dist-info/RECORD
