Metadata-Version: 2.1
Name: n2v
Version: 0.3.3
Summary: Noise2Void allows the training of a denoising CNN from individual noisy images. This implementationextends CSBDeep.
Home-page: https://github.com/juglab/n2v/
Author: Tim-Oliver Buchholz, Alexander Krull
Author-email: tim-oliver.buchholz@fmi.ch, a.f.f.krull@bham.ac.uk
License: BSD 3-Clause License
Project-URL: Repository, https://github.com/juglab/n2v/
Classifier: Development Status :: 4 - Beta
Classifier: Intended Audience :: Science/Research
Classifier: Topic :: Scientific/Engineering
Classifier: License :: OSI Approved :: BSD License
Classifier: Programming Language :: Python :: 3.7
Classifier: Programming Language :: Python :: 3.8
Classifier: Programming Language :: Python :: 3.9
Classifier: Programming Language :: Python :: 3.10
License-File: LICENSE.txt
Requires-Dist: numpy
Requires-Dist: tifffile
Requires-Dist: imagecodecs >=2020.2.18
Requires-Dist: csbdeep <0.8.0,>=0.7.2
Requires-Dist: Pillow
Requires-Dist: ruamel.yaml >=0.16.10
Requires-Dist: bioimageio.core
Requires-Dist: backports.tempfile ; python_version < "3.4"
Provides-Extra: testing
Requires-Dist: pytest ; extra == 'testing'
